Metadata-Version: 1.0
Name: Godot
Version: 0.1.1
Summary: Python implementation of the DOT language with Traits.
Home-page: http://rwl.github.com/godot
Author: Richard W. Lincoln
Author-email: r.w.lincoln@gmail.com
License: MIT
Platform: UNKNOWN
